bino/__init__.py
bino/bino.py
bino-0.0.1.dist-info/LICENSE.txt
bino-0.0.1.dist-info/METADATA
bino-0.0.1.dist-info/WHEEL
bino-0.0.1.dist-info/top_level.txt
bino-0.0.1.dist-info/RECORD
